autograms/__init__.py
autograms/autogram.py
autograms/autogram_config.py
autograms/autograms_subprocess.py
autograms/functional.py
autograms/memory.py
autograms/nodes.py
autograms/processors.py
autograms/program_control.py
autograms/run_subprocess.py
autograms/agent_modules/__init__.py
autograms/agent_modules/search_utils.py
autograms/apis/__init__.py
autograms/apis/openai_models.py
autograms/autogram_utils/__init__.py
autograms/autogram_utils/code_utils.py
autograms/autogram_utils/post_process_utils.py
autograms/autogram_utils/prompt_utils.py
autograms/graph_utils/__init__.py
autograms/graph_utils/graph.py
autograms/graph_utils/template.html
autograms-0.5.3.dist-info/METADATA
autograms-0.5.3.dist-info/WHEEL
autograms-0.5.3.dist-info/top_level.txt
autograms-0.5.3.dist-info/RECORD
