Metadata-Version: 2.1
Name: autograms
Version: 0.5.3
Summary: A framework for programming stateful LLM based chatbots.
Home-page: https://github.com/autograms/autograms
Classifier: Programming Language :: Python :: 3
Classifier: License :: OSI Approved :: BSD License
Requires-Python: >=3.9
Requires-Dist: openai
Requires-Dist: tiktoken
Requires-Dist: pandas
Requires-Dist: numpy
Requires-Dist: graphviz
Requires-Dist: setuptools
Requires-Dist: dill
